{
  "roubos": {
    "CC": "15:14|11/07/2026",
    "BPS": "18:36|11/07/2026",
    "ILHA": "14:03|11/07/2026",
    "CASSINO": "EM_ANDAMENTO",
    "BLS": "12:22|11/07/2026",
    "NAVIO": "13:53|11/07/2026",
    "BARSF": "12:33|11/07/2026",
    "LA1": "12:15|11/07/2026",
    "LA2": "12:12|11/07/2026",
    "LA3": "12:35|11/07/2026",
    "MOTEL": "DISPONIVEL",
    "PUTEIRO": "DISPONIVEL",
    "CAIXA": "13:38|11/07/2026",
    "LOTSF": "12:38|11/07/2026",
    "LOTLS": "12:18|11/07/2026"
  },
  "atualizadoEm": "2026-07-11T14:50:58.507Z"
}