{
  "roubos": {
    "CC": "EM_ANDAMENTO",
    "BPS": "14:56|10/06/2026",
    "ILHA": "DISPONIVEL",
    "CASSINO": "08:10|10/06/2026",
    "BLS": "08:17|10/06/2026",
    "NAVIO": "07:57|10/06/2026",
    "BARSF": "07:31|10/06/2026",
    "LA1": "08:11|10/06/2026",
    "LA2": "08:28|10/06/2026",
    "LA3": "07:28|10/06/2026",
    "MOTEL": "08:31|10/06/2026",
    "PUTEIRO": "08:24|10/06/2026",
    "CAIXA": "08:21|10/06/2026",
    "LOTSF": "DISPONIVEL",
    "LOTLS": "08:20|10/06/2026"
  },
  "atualizadoEm": "2026-06-10T09:23:20.050Z"
}