{
  "roubos": {
    "CC": "16:52|28/06/2026",
    "BPS": "21:44|28/06/2026",
    "ILHA": "EM_ANDAMENTO",
    "CASSINO": "16:18|28/06/2026",
    "BLS": "14:50|28/06/2026",
    "NAVIO": "DISPONIVEL",
    "BARSF": "18:26|28/06/2026",
    "LA1": "18:09|28/06/2026",
    "LA2": "18:35|28/06/2026",
    "LA3": "18:20|28/06/2026",
    "MOTEL": "DISPONIVEL",
    "PUTEIRO": "18:23|28/06/2026",
    "CAIXA": "18:36|28/06/2026",
    "LOTSF": "18:23|28/06/2026",
    "LOTLS": "15:38|28/06/2026"
  },
  "atualizadoEm": "2026-06-28T17:01:52.459Z"
}