{
  "roubos": {
    "CC": "DISPONIVEL",
    "BPS": "DISPONIVEL",
    "ILHA": "03:19|21/06/2026",
    "CASSINO": "03:05|21/06/2026",
    "BLS": "03:18|21/06/2026",
    "NAVIO": "03:31|21/06/2026",
    "BARSF": "03:21|21/06/2026",
    "LA1": "02:23|21/06/2026",
    "LA2": "03:32|21/06/2026",
    "LA3": "03:22|21/06/2026",
    "MOTEL": "03:36|21/06/2026",
    "PUTEIRO": "03:10|21/06/2026",
    "CAIXA": "03:10|21/06/2026",
    "LOTSF": "03:24|21/06/2026",
    "LOTLS": "03:21|21/06/2026"
  },
  "atualizadoEm": "2026-06-21T04:06:29.897Z"
}