{
  "roubos": {
    "CC": "09:50|17/07/2026",
    "BPS": "11:44|17/07/2026",
    "ILHA": "08:49|17/07/2026",
    "CASSINO": "08:57|17/07/2026",
    "BLS": "10:25|17/07/2026",
    "NAVIO": "DISPONIVEL",
    "BARSF": "11:07|17/07/2026",
    "LA1": "DISPONIVEL",
    "LA2": "DISPONIVEL",
    "LA3": "11:11|17/07/2026",
    "MOTEL": "DISPONIVEL",
    "PUTEIRO": "DISPONIVEL",
    "CAIXA": "09:21|17/07/2026",
    "LOTSF": "11:14|17/07/2026",
    "LOTLS": "DISPONIVEL"
  },
  "atualizadoEm": "2026-07-17T11:44:05.142Z"
}