{
  "roubos": {
    "CC": "02:27|12/07/2026",
    "BPS": "07:28|12/07/2026",
    "ILHA": "DISPONIVEL",
    "CASSINO": "DISPONIVEL",
    "BLS": "EM_ANDAMENTO",
    "NAVIO": "01:21|12/07/2026",
    "BARSF": "01:02|12/07/2026",
    "LA1": "DISPONIVEL",
    "LA2": "DISPONIVEL",
    "LA3": "00:58|12/07/2026",
    "MOTEL": "DISPONIVEL",
    "PUTEIRO": "DISPONIVEL",
    "CAIXA": "00:57|12/07/2026",
    "LOTSF": "01:08|12/07/2026",
    "LOTLS": "DISPONIVEL"
  },
  "atualizadoEm": "2026-07-12T01:54:30.435Z"
}