{
  "roubos": {
    "CC": "17:57|08/06/2026",
    "BPS": "23:21|08/06/2026",
    "ILHA": "DISPONIVEL",
    "CASSINO": "15:37|08/06/2026",
    "BLS": "16:41|08/06/2026",
    "NAVIO": "15:22|08/06/2026",
    "BARSF": "15:25|08/06/2026",
    "LA1": "DISPONIVEL",
    "LA2": "DISPONIVEL",
    "LA3": "15:28|08/06/2026",
    "MOTEL": "DISPONIVEL",
    "PUTEIRO": "DISPONIVEL",
    "CAIXA": "EM_ANDAMENTO",
    "LOTSF": "DISPONIVEL",
    "LOTLS": "DISPONIVEL"
  },
  "atualizadoEm": "2026-06-08T17:44:06.741Z"
}