{
  "roubos": {
    "CC": "17:10|21/06/2026",
    "BPS": "19:04|21/06/2026",
    "ILHA": "16:40|21/06/2026",
    "CASSINO": "EM_ANDAMENTO",
    "BLS": "DISPONIVEL",
    "NAVIO": "15:59|21/06/2026",
    "BARSF": "DISPONIVEL",
    "LA1": "16:20|21/06/2026",
    "LA2": "16:02|21/06/2026",
    "LA3": "16:46|21/06/2026",
    "MOTEL": "DISPONIVEL",
    "PUTEIRO": "DISPONIVEL",
    "CAIXA": "DISPONIVEL",
    "LOTSF": "16:24|21/06/2026",
    "LOTLS": "DISPONIVEL"
  },
  "atualizadoEm": "2026-06-21T17:17:37.416Z"
}