{
  "roubos": {
    "CC": "01:46|26/06/2026",
    "BPS": "06:14|26/06/2026",
    "ILHA": "DISPONIVEL",
    "CASSINO": "DISPONIVEL",
    "BLS": "DISPONIVEL",
    "NAVIO": "DISPONIVEL",
    "BARSF": "01:57|26/06/2026",
    "LA1": "DISPONIVEL",
    "LA2": "DISPONIVEL",
    "LA3": "01:01|26/06/2026",
    "MOTEL": "01:47|26/06/2026",
    "PUTEIRO": "DISPONIVEL",
    "CAIXA": "DISPONIVEL",
    "LOTSF": "01:44|26/06/2026",
    "LOTLS": "01:07|26/06/2026"
  },
  "atualizadoEm": "2026-06-26T02:57:07.567Z"
}