{
  "roubos": {
    "CC": "DISPONIVEL",
    "BPS": "17:41|03/07/2026",
    "ILHA": "17:42|03/07/2026",
    "CASSINO": "DISPONIVEL",
    "BLS": "DISPONIVEL",
    "NAVIO": "17:59|03/07/2026",
    "BARSF": "18:06|03/07/2026",
    "LA1": "DISPONIVEL",
    "LA2": "DISPONIVEL",
    "LA3": "18:08|03/07/2026",
    "MOTEL": "18:15|03/07/2026",
    "PUTEIRO": "19:04|03/07/2026",
    "CAIXA": "DISPONIVEL",
    "LOTSF": "19:30|03/07/2026",
    "LOTLS": "18:34|03/07/2026"
  },
  "atualizadoEm": "2026-07-03T20:00:44.123Z"
}