{
  "roubos": {
    "CC": "19:59|12/07/2026",
    "BPS": "DISPONIVEL",
    "ILHA": "EM_ANDAMENTO",
    "CASSINO": "18:41|12/07/2026",
    "BLS": "19:22|12/07/2026",
    "NAVIO": "18:02|12/07/2026",
    "BARSF": "18:07|12/07/2026",
    "LA1": "19:10|12/07/2026",
    "LA2": "DISPONIVEL",
    "LA3": "18:53|12/07/2026",
    "MOTEL": "DISPONIVEL",
    "PUTEIRO": "19:16|12/07/2026",
    "CAIXA": "00:04|13/07/2026",
    "LOTSF": "18:58|12/07/2026",
    "LOTLS": "19:28|12/07/2026"
  },
  "atualizadoEm": "2026-07-12T20:25:07.590Z"
}