{
  "roubos": {
    "CC": "10:43|23/07/2026",
    "BPS": "DISPONIVEL",
    "ILHA": "09:34|23/07/2026",
    "CASSINO": "DISPONIVEL",
    "BLS": "DISPONIVEL",
    "NAVIO": "09:42|23/07/2026",
    "BARSF": "09:52|23/07/2026",
    "LA1": "DISPONIVEL",
    "LA2": "EM_ANDAMENTO",
    "LA3": "09:50|23/07/2026",
    "MOTEL": "09:33|23/07/2026",
    "PUTEIRO": "09:32|23/07/2026",
    "CAIXA": "09:51|23/07/2026",
    "LOTSF": "09:47|23/07/2026",
    "LOTLS": "DISPONIVEL"
  },
  "atualizadoEm": "2026-07-23T11:05:25.528Z"
}