{
  "roubos": {
    "CC": "05:10|14/07/2026",
    "BPS": "08:17|14/07/2026",
    "ILHA": "05:04|14/07/2026",
    "CASSINO": "DISPONIVEL",
    "BLS": "05:42|14/07/2026",
    "NAVIO": "DISPONIVEL",
    "BARSF": "07:21|14/07/2026",
    "LA1": "DISPONIVEL",
    "LA2": "DISPONIVEL",
    "LA3": "07:24|14/07/2026",
    "MOTEL": "DISPONIVEL",
    "PUTEIRO": "DISPONIVEL",
    "CAIXA": "DISPONIVEL",
    "LOTSF": "07:27|14/07/2026",
    "LOTLS": "DISPONIVEL"
  },
  "atualizadoEm": "2026-07-14T07:57:03.510Z"
}