{
  "roubos": {
    "CC": "11:18|02/07/2026",
    "BPS": "15:26|02/07/2026",
    "ILHA": "DISPONIVEL",
    "CASSINO": "11:57|02/07/2026",
    "BLS": "11:17|02/07/2026",
    "NAVIO": "13:11|02/07/2026",
    "BARSF": "12:44|02/07/2026",
    "LA1": "11:03|02/07/2026",
    "LA2": "11:11|02/07/2026",
    "LA3": "12:41|02/07/2026",
    "MOTEL": "11:09|02/07/2026",
    "PUTEIRO": "11:25|02/07/2026",
    "CAIXA": "DISPONIVEL",
    "LOTSF": "12:47|02/07/2026",
    "LOTLS": "11:22|02/07/2026"
  },
  "atualizadoEm": "2026-07-02T13:44:53.911Z"
}