{
  "roubos": {
    "CC": "14:05|06/07/2026",
    "BPS": "18:52|06/07/2026",
    "ILHA": "13:05|06/07/2026",
    "CASSINO": "13:22|06/07/2026",
    "BLS": "DISPONIVEL",
    "NAVIO": "12:49|06/07/2026",
    "BARSF": "13:02|06/07/2026",
    "LA1": "DISPONIVEL",
    "LA2": "DISPONIVEL",
    "LA3": "13:10|06/07/2026",
    "MOTEL": "DISPONIVEL",
    "PUTEIRO": "DISPONIVEL",
    "CAIXA": "DISPONIVEL",
    "LOTSF": "13:13|06/07/2026",
    "LOTLS": "DISPONIVEL"
  },
  "atualizadoEm": "2026-07-06T13:52:13.999Z"
}