{
  "MTDELAX-E67265AA": {
    "hwid": "MTDELAX-E67265AA",
    "nick": "IIlI",
    "servidor": "SV2",
    "ip": "45.174.214.33",
    "status": "✅ AUTORIZADO",
    "timestamp": "2026-06-21T18:13:33.895Z",
    "ultimo_login": "2026-06-29T22:01:44.129Z",
    "primeiro_login": "21/06/2026, 16:34:29",
    "nicks": [
      "diabo_CasH",
      "@satan",
      "@satan_cheaterYtb",
      "SkunkGold",
      "Zezinho_CasH",
      "Mavi_EastSide",
      "IIlI",
      "IIlIwwwww"
    ]
  },
  "DESKTOP--05A4BC94": {
    "nick": "sainsupremacy",
    "servidor": "SV1",
    "ip": "177.124.11.199",
    "status": "✅ AUTORIZADO",
    "ultimo_login": "2026-06-29T23:33:17.237Z",
    "primeiro_login": "21/06/2026, 13:03:43",
    "nicks": [
      "sainsupremacy"
    ]
  },
  "DESKTOP--3E612FCC": {
    "nick": "xitaai.Vaqueiro",
    "servidor": "SV1",
    "ip": "143.137.214.1",
    "status": "✅ AUTORIZADO",
    "ultimo_login": "2026-06-30T02:48:56.594Z",
    "primeiro_login": "21/06/2026, 09:46:09",
    "nicks": [
      "xitaai.TerroR",
      "xitaai",
      "kaviska",
      "Rickrlk",
      "xitaai.Vaqueiro"
    ]
  },
  "SESH-SER-5DB2E370": {
    "nick": "Augusto_carrara",
    "servidor": "SV2",
    "ip": "200.192.18.55",
    "status": "✅ AUTORIZADO",
    "ultimo_login": "2026-06-30T02:44:14.447Z",
    "primeiro_login": "21/06/2026, 04:18:19",
    "nicks": [
      "Sesh",
      "151.242.227.116",
      "Redbull157",
      "Sonic_SkyyVodka",
      "BatoreMeiota",
      "yCalica",
      "Jack_Asaf_Jack",
      "yCalicannn",
      "xD_D",
      "IceCoolNego",
      "IceCoolNigga",
      "SonicSkyyVodka",
      "cupretodasilva",
      "ClaudeSpeed",
      "LaminaDoCaos",
      "Artg71DoECA",
      "COCOZZAO",
      "TOMA_SoBareBack",
      "saddam.lua",
      "Saddam.lua",
      "florentina_safadinha",
      "Dicionario_Xit",
      "sotemxit",
      "misandropi4",
      "AgaEssi",
      "npegouomod",
      "voltei_Bitch",
      "birinaite",
      "Voltei_Bitch",
      "Ganeshaaa",
      "comunists",
      "Unfadded2026",
      "SpeedRacer7",
      "natalia_fucci",
      "join_the_game",
      "cammuflage_bronco",
      "BlackMoldBR",
      "jorgin_dugrau",
      "carollina_herreira",
      "Nuance_Assemblador",
      "Augusto_carrara"
    ]
  },
  "4190E9D5691B6057": {
    "nick": "iOrioon_AltaClasse",
    "modelo": "SM-A217M",
    "marca": "samsung",
    "android": "12",
    "servidor": "SV2",
    "status": "✅ AUTORIZADO",
    "ultimo_login": "2026-06-24T13:45:36.518Z",
    "primeiro_login": "20/06/2026, 14:38:55",
    "nicks": [
      "iOrionn_AltaClasse",
      "iOrioon_AltaClasse"
    ]
  },
  "0F84F33317BE1740": {
    "nick": "brooksfield",
    "modelo": "2410FPCC5G",
    "marca": "POCO",
    "android": "16",
    "servidor": "SV2",
    "status": "✅ AUTORIZADO",
    "ultimo_login": "2026-06-20T05:31:46.756Z",
    "primeiro_login": "20/06/2026, 02:31:46",
    "nicks": [
      "lipemilgrau",
      "brooksfield"
    ]
  },
  "BFE6946C0238FA40": {
    "nick": "Lz.hwd",
    "modelo": "moto g75 5G",
    "marca": "motorola",
    "android": "16",
    "servidor": "SV2",
    "status": "❌ NEGADO",
    "ultimo_login": "2026-06-19T17:17:52.990Z",
    "primeiro_login": "19/06/2026, 14:17:52",
    "nicks": [
      "Lz.hwd"
    ]
  },
  "4E1DDA966F0D6DBD": {
    "nick": "Cowboy.CasH",
    "modelo": "SM-A065M",
    "marca": "samsung",
    "android": "16",
    "servidor": "SV2",
    "status": "❌ NEGADO",
    "ultimo_login": "2026-06-19T17:15:28.493Z",
    "primeiro_login": "19/06/2026, 14:15:28",
    "nicks": [
      "Cowboy.CasH"
    ]
  },
  "E56A58A151CD2689": {
    "nick": "YamahaSpecT",
    "modelo": "moto g23",
    "marca": "motorola",
    "android": "14",
    "servidor": "SV2",
    "status": "✅ AUTORIZADO",
    "ultimo_login": "2026-06-28T11:54:36.834Z",
    "primeiro_login": "18/06/2026, 20:36:49",
    "nicks": [
      "YamahaSpecT"
    ]
  },
  "BE4DF3F7412A876A": {
    "nick": "vinimilgrau",
    "modelo": "moto g(9) play",
    "marca": "motorola",
    "android": "11",
    "servidor": "SV2",
    "status": "✅ AUTORIZADO",
    "ultimo_login": "2026-06-26T05:33:40.287Z",
    "primeiro_login": "18/06/2026, 20:23:31",
    "nicks": [
      "vinimilgrau"
    ]
  },
  "49B4246A8C83C8C4": {
    "nick": "T3RROR1ST4",
    "modelo": "Redmi Note 9S",
    "marca": "Redmi",
    "android": "12",
    "servidor": "SV2",
    "status": "✅ AUTORIZADO",
    "ultimo_login": "2026-06-18T10:56:03.357Z",
    "primeiro_login": "18/06/2026, 07:56:03",
    "nicks": [
      "T3RROR1ST4"
    ]
  },
  "C0389161B17B9331": {
    "nick": "Sesh ADM",
    "modelo": "SM-A325M",
    "marca": "samsung",
    "android": "12",
    "servidor": "SV1",
    "status": "✅ AUTORIZADO",
    "ultimo_login": "2026-06-18T00:11:56.872Z",
    "primeiro_login": "17/06/2026, 21:11:56",
    "nicks": [
      "Sesh ADM"
    ]
  },
  "690E0F80D3CE1D6D": {
    "nick": "Narciso teste",
    "modelo": "SM-A065M",
    "marca": "samsung",
    "android": "14",
    "servidor": "SV1",
    "status": "✅ AUTORIZADO",
    "ultimo_login": "2026-06-17T21:38:48.037Z",
    "primeiro_login": "17/06/2026, 18:38:48",
    "nicks": [
      "Narciso teste"
    ]
  },
  "1C09F2088941D7B4": {
    "nick": "teste 2",
    "modelo": "SM-A022M",
    "marca": "samsung",
    "android": "11",
    "servidor": "SV2",
    "status": "✅ AUTORIZADO",
    "ultimo_login": "2026-06-17T20:05:20.954Z",
    "primeiro_login": "17/06/2026, 17:05:20",
    "nicks": [
      "teste",
      "teste 2"
    ]
  },
  "5DBAF9F1B605A8DA": {
    "nick": "Rzz",
    "modelo": "moto g54 5G",
    "marca": "motorola",
    "android": "15",
    "servidor": "SV2",
    "status": "❌ NEGADO",
    "ultimo_login": "2026-06-17T19:33:48.805Z",
    "primeiro_login": "17/06/2026, 16:33:48",
    "nicks": [
      "Rzz"
    ]
  },
  "085759D419F0FB1F": {
    "nick": "Sesh Adm",
    "modelo": "SM-A325M",
    "marca": "samsung",
    "android": "12",
    "servidor": "SV2",
    "status": "✅ AUTORIZADO",
    "ultimo_login": "2026-06-15T06:17:28.020Z",
    "primeiro_login": "15/06/2026, 03:17:28",
    "nicks": [
      "Sesh Adm"
    ]
  },
  "5DB2E370": {
    "nick": "?",
    "timestamp": "2026-06-27T10:45:54.143Z",
    "nicks": [
      "?"
    ],
    "primeiro_login": "2026-06-27T10:45:56.097Z",
    "ultimo_login": "2026-06-27T10:48:23.701Z",
    "status": "Sem dados cadastrais no infos.json."
  },
  "REVISION-F584DBCD": {
    "nick": "Amaral_Vaqueiro",
    "servidor": "SV1",
    "ip": "177.11.247.51",
    "status": "❌ NEGADO",
    "nicks": [
      "Amaral_Vaqueiro"
    ],
    "primeiro_login": "2026-06-23T22:51:21.765Z",
    "ultimo_login": "2026-06-23T22:51:21.765Z"
  },
  "3E612FCC": {
    "nick": "?",
    "timestamp": "2026-06-21T19:51:20.213Z",
    "nicks": [
      "?"
    ],
    "primeiro_login": "2026-06-27T10:48:40.660Z",
    "ultimo_login": "2026-06-27T19:41:09.334Z"
  }
}